MANIFEST.in
README.md
requirements.txt
setup.cfg
setup.py
ecd/__init__.py
ecd/main.py
ecd.egg-info/PKG-INFO
ecd.egg-info/SOURCES.txt
ecd.egg-info/dependency_links.txt
ecd.egg-info/entry_points.txt
ecd.egg-info/not-zip-safe
ecd.egg-info/requires.txt
ecd.egg-info/top_level.txt
ecd/common_tools/__init__.py
ecd/common_tools/create_logger.py
ecd/common_tools/decrator_tools.py
ecd/common_tools/io_tools.py
ecd/concurrent_p_t/__init__.py
ecd/concurrent_p_t/pressure_base.py
ecd/concurrent_p_t/example/__init__.py
ecd/concurrent_p_t/example/pressure_api.py
ecd/concurrent_p_t/example/simple_api.py
ecd/db_tools/__init__.py
ecd/db_tools/mongo_db.py
ecd/db_tools/redis_db.py
ecd/password_manage/__init__.py
ecd/password_manage/run.py
ecd/password_manage/app/__init__.py
ecd/password_manage/app/clipboard_monitor.py
ecd/password_manage/app/handle_data.py
ecd/password_manage/app/password_web.py
ecd/password_manage/app/static/css/suggestion.css
ecd/password_manage/app/static/js/bloodhound.js
ecd/password_manage/app/static/js/jquery.min.js
ecd/password_manage/app/static/js/typeahead.bundle.js
ecd/password_manage/app/templates/index.html
ecd/password_manage/app/templates/old.html
ecd/send_email_attachments/__init__.py
ecd/send_email_attachments/email_conf.py
ecd/send_email_attachments/send_email.py
ecd/spider_tools/__init__.py
ecd/spider_tools/get_proxy.py
ecd/spider_tools/user_agents.py