Metadata-Version: 1.2
Name: ecd
Version: 0.1.196
Summary: the english translate tool
Home-page: https://github.com/sixiyizai/ecd
Author: sixiyizai
Author-email: lingyunzou@aliyun.com
License: MIT
Keywords: english to chinese dictionary
Platform: UNKNOWN
Classifier: Programming Language :: Python :: 3
Requires-Python: >=3.0
